pysld/__init__.py
pysld/__version__.py
pysld/categorizedStyle.py
pysld/classification.py
pysld/classifiedStyle.py
pysld/featureLabel.py
pysld/postgres.py
pysld/rasterStyle.py
pysld/simpleStyle.py
pysld/style.py
pysld/support.py
style/__init__.py
style/__version__.py
style/catagorizedStyle.py
style/categorizedStyle.py
style/classification.py
style/classifiedStyle.py
style/featureLabel.py
style/postgres.py
style/rasterStyle.py
style/simpleStyle.py
style/style.py
style/support.py
pysld-0.0.6.dist-info/LICENSE
pysld-0.0.6.dist-info/METADATA
pysld-0.0.6.dist-info/WHEEL
pysld-0.0.6.dist-info/top_level.txt
pysld-0.0.6.dist-info/RECORD
