Metadata-Version: 2.1
Name: pysld
Version: 0.0.6
Summary: Package for SLD generator
Home-page: https://github.com/iamtekson/pysld
Author: Tek Kshetri
Author-email: iamtekson@gmail.com
License: MIT License
Keywords: pysld,sld,style,cartography,geoserver
Platform: UNKNOWN
Classifier: Programming Language :: Python :: 3
Classifier: Intended Audience :: Developers
Classifier: Intended Audience :: Science/Research
Classifier: License :: OSI Approved :: MIT License
Classifier: Operating System :: OS Independent
Requires-Python: >=3.6
Requires-Dist: cycler (==0.10.0)
Requires-Dist: jenkspy (==0.2.0)
Requires-Dist: kiwisolver (==1.3.1)
Requires-Dist: matplotlib (==3.2.0)
Requires-Dist: numpy (==1.20.2)
Requires-Dist: pandas (==1.2.3)
Requires-Dist: Pillow (==8.2.0)
Requires-Dist: psycopg2 (==2.8.6)
Requires-Dist: pyparsing (==2.4.7)
Requires-Dist: python-dateutil (==2.8.1)
Requires-Dist: pytz (==2021.1)
Requires-Dist: scipy (==1.6.2)
Requires-Dist: seaborn (==0.11.1)
Requires-Dist: six (==1.15.0)
Provides-Extra: dev
Requires-Dist: bleach (==3.3.0) ; extra == 'dev'
Requires-Dist: certifi (==2020.12.5) ; extra == 'dev'
Requires-Dist: chardet (==4.0.0) ; extra == 'dev'
Requires-Dist: colorama (==0.4.4) ; extra == 'dev'
Requires-Dist: cycler (==0.10.0) ; extra == 'dev'
Requires-Dist: docutils (==0.17) ; extra == 'dev'
Requires-Dist: idna (==2.10) ; extra == 'dev'
Requires-Dist: importlib-metadata (==3.10.0) ; extra == 'dev'
Requires-Dist: jenkspy (==0.2.0) ; extra == 'dev'
Requires-Dist: keyring (==23.0.1) ; extra == 'dev'
Requires-Dist: kiwisolver (==1.3.1) ; extra == 'dev'
Requires-Dist: matplotlib (==3.2.0) ; extra == 'dev'
Requires-Dist: numpy (==1.20.2) ; extra == 'dev'
Requires-Dist: packaging (==20.9) ; extra == 'dev'
Requires-Dist: pandas (==1.2.3) ; extra == 'dev'
Requires-Dist: Pillow (==8.2.0) ; extra == 'dev'
Requires-Dist: pkginfo (==1.7.0) ; extra == 'dev'
Requires-Dist: psycopg2 (==2.8.6) ; extra == 'dev'
Requires-Dist: Pygments (==2.8.1) ; extra == 'dev'
Requires-Dist: pyparsing (==2.4.7) ; extra == 'dev'
Requires-Dist: python-dateutil (==2.8.1) ; extra == 'dev'
Requires-Dist: pytz (==2021.1) ; extra == 'dev'
Requires-Dist: pywin32-ctypes (==0.2.0) ; extra == 'dev'
Requires-Dist: readme-renderer (==29.0) ; extra == 'dev'
Requires-Dist: requests (==2.25.1) ; extra == 'dev'
Requires-Dist: requests-toolbelt (==0.9.1) ; extra == 'dev'
Requires-Dist: rfc3986 (==1.4.0) ; extra == 'dev'
Requires-Dist: scipy (==1.6.2) ; extra == 'dev'
Requires-Dist: seaborn (==0.11.1) ; extra == 'dev'
Requires-Dist: six (==1.15.0) ; extra == 'dev'
Requires-Dist: tqdm (==4.60.0) ; extra == 'dev'
Requires-Dist: twine (==3.4.1) ; extra == 'dev'
Requires-Dist: urllib3 (==1.26.4) ; extra == 'dev'
Requires-Dist: webencodings (==0.5.1) ; extra == 'dev'
Requires-Dist: zipp (==3.4.1) ; extra == 'dev'
